polymera/__init__.py
polymera/polymera.py
polymera/bio/__init__.py
polymera/bio/dna.py
polymera/bio/protein.py
polymera-0.1.3.dist-info/licenses/LICENSE
tests/test_polymera.py
tests/test_bio/test_dna.py
tests/test_bio/test_protein.py
polymera-0.1.3.dist-info/METADATA
polymera-0.1.3.dist-info/WHEEL
polymera-0.1.3.dist-info/top_level.txt
polymera-0.1.3.dist-info/RECORD
