Metadata-Version: 2.4
Name: polymera
Version: 0.1.3
Summary: Representing ambiguous sequences written with complement alphabets.
Author: Peter Vegh
License-Expression: MIT
Project-URL: Homepage, https://github.com/Edinburgh-Genome-Foundry/polymera
Keywords: biology,sequence,DNA
License-File: LICENSE
Dynamic: license-file
